{
  "hash_message": "f7beb9394aa29c8e1b3f7bf45f0680f9",
  "content_message": "УВАГА! ВАЖЛИВА ІНФОРМАЦІЯ!\nНа 13:30 30.11.2025р. НЕК \"Укренерго\" змінив застосування кількості черг:\nз 14:00 до 15:00 - 1,5 черги\nз 15:00 до 20:00 - 2,5 черги\nз 20:00 до 22:00 - 1,5 черги\nз 22:00 до 23:00 - 0,5 черги\nПошук черги та підчерги за адресою",
  "content_date": "Дата оновлення інформації - 14:30 30.11.2025",
  "screenshot_hash": "787d36285f02f65ad699802b0c58982d",
  "timestamp": "2025-11-30T12:34:37.131518"
}